flexi_socket/__init__.py
flexi_socket/client_classifier.py
flexi_socket/connection.py
flexi_socket/constraints.py
flexi_socket/flexi_socket.py
flexi_socket/message.py
flexi_socket/message_packaging.py
flexi_socket-0.0.10.dist-info/METADATA
flexi_socket-0.0.10.dist-info/WHEEL
flexi_socket-0.0.10.dist-info/top_level.txt
flexi_socket-0.0.10.dist-info/RECORD
